{"admire_auth": {"admire_button": 0, "is_admire": 0, "is_show_admire_button": 0, "is_show_admire_tab": 0}, "anchors": null, "author": {"avatar_thumb": {"height": 720, "uri": "100x100/aweme-avatar/douyin-user-file_61348cd4eae709101c87a2e1a6a444d0", "url_list": ["https://p26.douyinpic.com/aweme/100x100/aweme-avatar/douyin-user-file_61348cd4eae709101c87a2e1a6a444d0.webp?from=116350172", "https://p6.douyinpic.com/aweme/100x100/aweme-avatar/douyin-user-file_61348cd4eae709101c87a2e1a6a444d0.webp?from=116350172", "https://p11.douyinpic.com/aweme/100x100/aweme-avatar/douyin-user-file_61348cd4eae709101c87a2e1a6a444d0.webp?from=116350172", "https://p26.douyinpic.com/aweme/100x100/aweme-avatar/douyin-user-file_61348cd4eae709101c87a2e1a6a444d0.jpeg?from=116350172"], "width": 720}, "cf_list": null, "close_friend_type": 0, "contacts_status": 1, "contrail_list": null, "cover_url": [{"height": 720, "uri": "c8510002be9a3a61aad2", "url_list": ["https://p6-sign.douyinpic.com/obj/c8510002be9a3a61aad2?x-expires=1673690400&x-signature=g7Cv09EfpOapru9gn%2B%2BjVqeP5gA%3D&from=116350172", "https://p26-sign.douyinpic.com/obj/c8510002be9a3a61aad2?x-expires=1673690400&x-signature=tmpNnwqiYgueviOK9ymKIURHyEU%3D&from=116350172", "https://p9-sign.douyinpic.com/obj/c8510002be9a3a61aad2?x-expires=1673690400&x-signature=idN12%2B7lU4%2BoZxvccdStbLoaZEQ%3D&from=116350172"], "width": 720}], "create_time": 0, "custom_verify": "", "data_label_list": null, "endorsement_info_list": null, "enterprise_verify_reason": "", "favoriting_count": 28040, "follow_status": 0, "follower_count": 0, "follower_list_secondary_information_struct": null, "follower_status": 0, "following_count": 0, "im_role_ids": null, "is_ad_fake": false, "is_blocked_v2": false, "is_blocking_v2": false, "is_cf": 0, "max_follower_count": 0, "nickname": "小霞民间艺术团", "not_seen_item_id_list": null, "not_seen_item_id_list_v2": null, "offline_info_list": null, "personal_tag_list": null, "prevent_download": false, "risk_notice_text": "", "sec_uid": "MS4wLjABAAAA9eXBkBHtMzY0CEqQPimZHo65NXfcv9umWDhhP2yh0GU", "secret": 0, "share_info": {"share_desc": "", "share_desc_info": "", "share_qrcode_url": {"height": 720, "uri": "6f8f000cf5d06e8eab58", "url_list": ["https://p3-sign.douyinpic.com/obj/6f8f000cf5d06e8eab58?x-expires=1672502400&x-signature=340%2FBn9U4niwOrGj2N3Ps95%2Fafs%3D&from=116350172", "https://p9-sign.douyinpic.com/obj/6f8f000cf5d06e8eab58?x-expires=1672502400&x-signature=dd1Gvj8XzmwFkIaDRbOSyqNdTIc%3D&from=116350172", "https://p26-sign.douyinpic.com/obj/6f8f000cf5d06e8eab58?x-expires=1672502400&x-signature=vmozPPE8u6zKiE8vCCJPiuWg72A%3D&from=116350172"], "width": 720}, "share_title": "", "share_title_myself": "", "share_title_other": "", "share_url": "", "share_weibo_desc": ""}, "short_id": "603391782", "signature": "闫小霞电话15135672973\n我从孩提时就喜欢看戏听音乐，还时不时象模象样地在大人面前卖弄一番。从此至今，说唱和表演就成了我生活中须臾不可离开的组成部分，象灵魂一样重要。从2015年以来，我组建了一个“小霞民间艺术团”，网罗喜欢文艺的粉男粉女，自编自导自演节目。下农村，到社区，进养老院；送欢乐，慰心灵，助慈善，传递社会正能量，尽自己微薄之力。在此，希望得到大家的关注和帮助。请为我们鼓劲加油吧！", "signature_extra": null, "special_people_labels": null, "status": 1, "text_extra": null, "total_favorited": 137806, "uid": "52895190404", "unique_id": "", "user_age": -1, "user_canceled": false, "user_permissions": null, "verification_type": 1}, "author_mask_tag": 0, "author_user_id": 52895190404, "aweme_acl": {"download_mask_panel": {"code": 1, "show_type": 0}}, "aweme_control": {"can_comment": true, "can_forward": true, "can_share": true, "can_show_comment": true}, "aweme_id": "7122817017895210243", "aweme_type": 0, "challenge_position": null, "chapter_list": null, "collect_stat": 0, "comment_gid": 7122817017895210243, "comment_list": null, "comment_permission_info": {"can_comment": true, "comment_permission_status": 0, "item_detail_entry": true, "press_entry": true, "toast_guide": false}, "commerce_config_data": null, "common_bar_info": "[]", "component_info_v2": "{\"desc_lines_limit\":0,\"hide_marquee\":false}", "cover_labels": null, "create_time": 1658410073, "desc": "传承中国非物质文化遗产 项目！，过去的正宗味的南村寨西秧歌，《打酸枣》。 #经典永流传 ！", "digg_lottie": {"can_bomb": 0, "lottie_id": ""}, "disable_relation_bar": 0, "dislike_dimension_list": null, "duet_aggregate_in_music_tab": false, "duration": 278315, "feed_comment_config": {"author_audit_status": 0, "input_config_text": "善语结善缘，恶言伤人心"}, "geofencing": [], "geofencing_regions": null, "group_id": "7120933116017003817", "horizontal_type": 1, "hybrid_label": null, "image_album_music_info": {"begin_time": 0, "end_time": 0, "volume": 0}, "image_infos": null, "image_list": null, "images": null, "img_bitrate": null, "impression_data": {"group_id_list_a": [7120933116017003817], "group_id_list_b": [7120933116017003817], "similar_id_list_a": null, "similar_id_list_b": null}, "interaction_stickers": null, "is_ads": false, "is_collects_selected": 0, "is_duet_sing": false, "is_image_beat": false, "is_life_item": false, "is_story": 0, "is_top": 0, "item_warn_notification": {"content": "", "show": false, "type": 0}, "label_top_text": null, "long_video": null, "music": {"album": "", "artist_user_infos": null, "artists": [], "audition_duration": 278, "author": "小霞民间艺术团", "author_deleted": false, "author_position": null, "author_status": 1, "avatar_large": {"height": 720, "uri": "1080x1080/aweme-avatar/douyin-user-file_61348cd4eae709101c87a2e1a6a444d0", "url_list": ["https://p11.douyinpic.com/aweme/1080x1080/aweme-avatar/douyin-user-file_61348cd4eae709101c87a2e1a6a444d0.webp?from=116350172", "https://p3.douyinpic.com/aweme/1080x1080/aweme-avatar/douyin-user-file_61348cd4eae709101c87a2e1a6a444d0.webp?from=116350172", "https://p26.douyinpic.com/aweme/1080x1080/aweme-avatar/douyin-user-file_61348cd4eae709101c87a2e1a6a444d0.webp?from=116350172", "https://p11.douyinpic.com/aweme/1080x1080/aweme-avatar/douyin-user-file_61348cd4eae709101c87a2e1a6a444d0.jpeg?from=116350172"], "width": 720}, "avatar_medium": {"height": 720, "uri": "720x720/aweme-avatar/douyin-user-file_61348cd4eae709101c87a2e1a6a444d0", "url_list": ["https://p3.douyinpic.com/aweme/720x720/aweme-avatar/douyin-user-file_61348cd4eae709101c87a2e1a6a444d0.webp?from=116350172", "https://p26.douyinpic.com/aweme/720x720/aweme-avatar/douyin-user-file_61348cd4eae709101c87a2e1a6a444d0.webp?from=116350172", "https://p11.douyinpic.com/aweme/720x720/aweme-avatar/douyin-user-file_61348cd4eae709101c87a2e1a6a444d0.webp?from=116350172", "https://p3.douyinpic.com/aweme/720x720/aweme-avatar/douyin-user-file_61348cd4eae709101c87a2e1a6a444d0.jpeg?from=116350172"], "width": 720}, "avatar_thumb": {"height": 720, "uri": "100x100/aweme-avatar/douyin-user-file_61348cd4eae709101c87a2e1a6a444d0", "url_list": ["https://p26.douyinpic.com/aweme/100x100/aweme-avatar/douyin-user-file_61348cd4eae709101c87a2e1a6a444d0.webp?from=116350172", "https://p11.douyinpic.com/aweme/100x100/aweme-avatar/douyin-user-file_61348cd4eae709101c87a2e1a6a444d0.webp?from=116350172", "https://p6.douyinpic.com/aweme/100x100/aweme-avatar/douyin-user-file_61348cd4eae709101c87a2e1a6a444d0.webp?from=116350172", "https://p26.douyinpic.com/aweme/100x100/aweme-avatar/douyin-user-file_61348cd4eae709101c87a2e1a6a444d0.jpeg?from=116350172"], "width": 720}, "binded_challenge_id": 0, "can_background_play": true, "collect_stat": 0, "cover_hd": {"height": 720, "uri": "1080x1080/aweme-avatar/douyin-user-file_61348cd4eae709101c87a2e1a6a444d0", "url_list": ["https://p11.douyinpic.com/aweme/1080x1080/aweme-avatar/douyin-user-file_61348cd4eae709101c87a2e1a6a444d0.webp?from=116350172", "https://p3.douyinpic.com/aweme/1080x1080/aweme-avatar/douyin-user-file_61348cd4eae709101c87a2e1a6a444d0.webp?from=116350172", "https://p26.douyinpic.com/aweme/1080x1080/aweme-avatar/douyin-user-file_61348cd4eae709101c87a2e1a6a444d0.webp?from=116350172", "https://p11.douyinpic.com/aweme/1080x1080/aweme-avatar/douyin-user-file_61348cd4eae709101c87a2e1a6a444d0.jpeg?from=116350172"], "width": 720}, "cover_large": {"height": 720, "uri": "1080x1080/aweme-avatar/douyin-user-file_61348cd4eae709101c87a2e1a6a444d0", "url_list": ["https://p11.douyinpic.com/aweme/1080x1080/aweme-avatar/douyin-user-file_61348cd4eae709101c87a2e1a6a444d0.webp?from=116350172", "https://p3.douyinpic.com/aweme/1080x1080/aweme-avatar/douyin-user-file_61348cd4eae709101c87a2e1a6a444d0.webp?from=116350172", "https://p26.douyinpic.com/aweme/1080x1080/aweme-avatar/douyin-user-file_61348cd4eae709101c87a2e1a6a444d0.webp?from=116350172", "https://p11.douyinpic.com/aweme/1080x1080/aweme-avatar/douyin-user-file_61348cd4eae709101c87a2e1a6a444d0.jpeg?from=116350172"], "width": 720}, "cover_medium": {"height": 720, "uri": "720x720/aweme-avatar/douyin-user-file_61348cd4eae709101c87a2e1a6a444d0", "url_list": ["https://p3.douyinpic.com/aweme/720x720/aweme-avatar/douyin-user-file_61348cd4eae709101c87a2e1a6a444d0.webp?from=116350172", "https://p26.douyinpic.com/aweme/720x720/aweme-avatar/douyin-user-file_61348cd4eae709101c87a2e1a6a444d0.webp?from=116350172", "https://p11.douyinpic.com/aweme/720x720/aweme-avatar/douyin-user-file_61348cd4eae709101c87a2e1a6a444d0.webp?from=116350172", "https://p3.douyinpic.com/aweme/720x720/aweme-avatar/douyin-user-file_61348cd4eae709101c87a2e1a6a444d0.jpeg?from=116350172"], "width": 720}, "cover_thumb": {"height": 720, "uri": "100x100/aweme-avatar/douyin-user-file_61348cd4eae709101c87a2e1a6a444d0", "url_list": ["https://p26.douyinpic.com/aweme/100x100/aweme-avatar/douyin-user-file_61348cd4eae709101c87a2e1a6a444d0.webp?from=116350172", "https://p11.douyinpic.com/aweme/100x100/aweme-avatar/douyin-user-file_61348cd4eae709101c87a2e1a6a444d0.webp?from=116350172", "https://p6.douyinpic.com/aweme/100x100/aweme-avatar/douyin-user-file_61348cd4eae709101c87a2e1a6a444d0.webp?from=116350172", "https://p26.douyinpic.com/aweme/100x100/aweme-avatar/douyin-user-file_61348cd4eae709101c87a2e1a6a444d0.jpeg?from=116350172"], "width": 720}, "dmv_auto_show": false, "dsp_status": 10, "duration": 278, "end_time": 0, "external_song_info": [], "extra": "{\"beats\":{},\"cover_colors\":null,\"is_red\":0,\"is_subsidy_exp\":false,\"music_label_id\":null,\"aggregate_exempt_conf\":[],\"reviewed\":0,\"douyin_beats_info\":{},\"extract_item_id\":7122817017895210243,\"with_aed_model\":1,\"dsp_switch\":0,\"review_unshelve_reason\":0,\"schedule_search_time\":0,\"has_edited\":0,\"hotsoon_review_time\":-1,\"music_tagging\":{\"Languages\":null,\"Moods\":null,\"Genres\":null,\"Themes\":null,\"AEDs\":null,\"SingingVersions\":null,\"Instruments\":null},\"is_aed_music\":0}", "id": 7122817046123268894, "id_str": "7122817046123268894", "is_audio_url_with_cookie": false, "is_commerce_music": false, "is_del_video": false, "is_matched_metadata": false, "is_original": false, "is_original_sound": true, "is_pgc": false, "is_restricted": false, "is_video_self_see": false, "luna_info": {"is_luna_user": false}, "lyric_short_position": null, "mid": "7122817046123268894", "music_chart_ranks": null, "music_status": 1, "musician_user_infos": null, "mute_share": false, "offline_desc": "", "owner_handle": "603391782", "owner_id": "52895190404", "owner_nickname": "小霞民间艺术团", "pgc_music_type": 2, "play_url": {"height": 720, "uri": "https://sf6-cdn-tos.douyinstatic.com/obj/ies-music/7122817046083406622.mp3", "url_key": "7122817046123268894", "url_list": ["https://sf6-cdn-tos.douyinstatic.com/obj/ies-music/7122817046083406622.mp3", "https://sf3-cdn-tos.douyinstatic.com/obj/ies-music/7122817046083406622.mp3"], "width": 720}, "position": null, "prevent_download": false, "prevent_item_download_status": 0, "preview_end_time": 0, "preview_start_time": 0, "reason_type": 0, "redirect": false, "schema_url": "", "search_impr": {"entity_id": "7122817046123268894"}, "sec_uid": "MS4wLjABAAAA9eXBkBHtMzY0CEqQPimZHo65NXfcv9umWDhhP2yh0GU", "shoot_duration": 278, "source_platform": 23, "start_time": 0, "status": 1, "tag_list": null, "title": "@小霞民间艺术团创作的原声", "unshelve_countries": null, "user_count": 0, "video_duration": 278}, "nickname_position": null, "origin_comment_ids": null, "origin_text_extra": [], "original_images": null, "packed_clips": null, "photo_search_entrance": {"ecom_type": 0}, "position": null, "press_panel_info": "[{\"interactive\":[\"2_story\",\"2_friend\"]},{\"feedback\":[\"rr_feedback\",\"dislike\",\"ignore\",\"block\",\"unfollow\",\"sever\",\"dislike_collect\"]},{\"control\":[\"speed\",\"auth\",\"delete\",\"save\",\"collect\",\"reward\",\"bg_play\",\"duet\",\"together\"]}]", "preview_title": "传承中国非物质文化遗产 项目！，过去的正宗味的南村寨西秧歌，《打酸枣》。 #经典永流传 ！", "preview_video_status": 1, "promotions": [], "rate": 10, "region": "CN", "relation_labels": null, "search_impr": {"entity_id": "7122817017895210243", "entity_type": "GENERAL"}, "series_paid_info": {"item_price": 0, "series_paid_status": 0}, "share_info": {"share_desc": "在抖音，记录美好生活", "share_desc_info": "#在抖音，记录美好生活#传承中国非物质文化遗产 项目！，过去的正宗味的南村寨西秧歌，《打酸枣》。 #经典永流传 ！", "share_link_desc": "5.12 ZMj:/ 复制打开抖音，看看【小霞民间艺术团的作品】传承中国非物质文化遗产 项目！，过去的正宗味的南村... %s", "share_url": "https://www.iesdouyin.com/share/video/7122817017895210243/?region=HK&mid=7122817046123268894&u_code=-1&did=MS4wLjABAAAANwkJuWIRFOzg5uCpDRpMj4OX-QryoDgn-yYlXQnRwQQ&iid=MS4wLjABAAAANwkJuWIRFOzg5uCpDRpMj4OX-QryoDgn-yYlXQnRwQQ&with_sec_did=1&titleType=title&from_ssr=1"}, "share_url": "https://www.iesdouyin.com/share/video/7122817017895210243/?region=HK&mid=7122817046123268894&u_code=-1&did=MS4wLjABAAAANwkJuWIRFOzg5uCpDRpMj4OX-QryoDgn-yYlXQnRwQQ&iid=MS4wLjABAAAANwkJuWIRFOzg5uCpDRpMj4OX-QryoDgn-yYlXQnRwQQ&with_sec_did=1&titleType=title&from_ssr=1", "should_open_ad_report": false, "show_follow_button": {}, "social_tag_list": null, "standard_bar_info_list": null, "statistics": {"admire_count": 0, "aweme_id": "7122817017895210243", "collect_count": 0, "comment_count": 7, "digg_count": 38, "play_count": 0, "share_count": 5}, "status": {"allow_share": true, "aweme_id": "7122817017895210243", "in_reviewing": false, "is_delete": false, "is_prohibited": false, "listen_video_status": 2, "part_see": 0, "private_status": 0, "review_result": {"review_status": 0}}, "text_extra": [{"end": 43, "hashtag_id": "1593014791751709", "hashtag_name": "经典永流传", "is_commerce": false, "start": 37, "type": 1}], "uniqid_position": null, "user_digged": 0, "video": {"big_thumbs": [{"duration": 278.266333, "fext": "jpg", "img_num": 278, "img_url": "https://p3-sign.douyinpic.com/tos-cn-p-0015/673c5aebb7624ddea5f56d655e427af4_1658410083~tplv-noop.image?x-expires=1672487512&x-signature=EQVMwzXKyYjfi22yPLBUHUp1h%2BQ%3D", "img_x_len": 10, "img_x_size": 240, "img_y_len": 28, "img_y_size": 136, "interval": 1, "uri": "tos-cn-p-0015/673c5aebb7624ddea5f56d655e427af4_1658410083"}], "bit_rate": [{"FPS": 30, "HDR_bit": "", "HDR_type": "", "bit_rate": 1263269, "gear_name": "adapt_lowest_720_1", "is_bytevc1": 1, "is_h265": 1, "play_addr": {"data_size": 43948364, "file_cs": "c:0-303764-9511|a:v0300fg10000cbcl7vjc77uahfnntpkg", "file_hash": "523659413cee7bdebc9be4d8057d3645", "height": 720, "uri": "v0300fg10000cbcl7vjc77uahfnntpkg", "url_key": "v0300fg10000cbcl7vjc77uahfnntpkg_bytevc1_720p_1263269", "url_list": ["https://v5-dy-o-abtest.zjcdn.com/a52d40e4a377858b3f3a1835be205f86/63b02258/video/tos/cn/tos-cn-ve-15c001-alinc2/c25a8670b59745e58a93529c1a5a7783/?a=1128&ch=26&cr=3&dr=0&lr=all&cd=0%7C0%7C0%7C3&cv=1&br=1233&bt=1233&cs=2&ds=3&ft=G__kkZZI0rd12NhGV---VozfuLYkDQIkaYlv&mime_type=video_mp4&qs=15&rc=NTVpNDNkZDg3ODQ7ZzkzOUBpanNxaWQ6ZnlvZTMzNGkzM0AtYzVeXmFjNjUxYjBeMWAyYSNocWtlcjRnNGBgLS1kLTBzcw%3D%3D&l=2022123118471393DDD44DD8533F737F96&btag=b0000&cc=46", "https://v26.douyinvod.com/d15fc88222424cdd191fdf94c9252fee/63b02258/video/tos/cn/tos-cn-ve-15c001-alinc2/c25a8670b59745e58a93529c1a5a7783/?a=1128&ch=26&cr=3&dr=0&lr=all&cd=0%7C0%7C0%7C3&cv=1&br=1233&bt=1233&cs=2&ds=3&ft=G__kkZZI0rd12NhGV---VozfuLYkDQIkaYlv&mime_type=video_mp4&qs=15&rc=NTVpNDNkZDg3ODQ7ZzkzOUBpanNxaWQ6ZnlvZTMzNGkzM0AtYzVeXmFjNjUxYjBeMWAyYSNocWtlcjRnNGBgLS1kLTBzcw%3D%3D&l=2022123118471393DDD44DD8533F737F96&btag=b0000&cc=2a", "https://api.amemv.com/aweme/v1/play/?video_id=v0300fg10000cbcl7vjc77uahfnntpkg&line=0&file_id=56c046ad38e1458495fadaa0a18ff202&sign=523659413cee7bdebc9be4d8057d3645&is_play_url=1&source=PackSourceEnum_AWEME_DETAIL", "https://api5-normal-dsa.amemv.com/aweme/v1/play/?video_id=v0300fg10000cbcl7vjc77uahfnntpkg&line=1&file_id=56c046ad38e1458495fadaa0a18ff202&sign=523659413cee7bdebc9be4d8057d3645&is_play_url=1&source=PackSourceEnum_AWEME_DETAIL"], "width": 1270}, "quality_type": 15}, {"FPS": 30, "HDR_bit": "", "HDR_type": "", "bit_rate": 1026722, "gear_name": "adapt_540_1", "is_bytevc1": 1, "is_h265": 1, "play_addr": {"data_size": 35719033, "file_cs": "c:0-303761-fd9b|a:v0300fg10000cbcl7vjc77uahfnntpkg", "file_hash": "d6e63b46fb16655c41aa00aa58cadc65", "height": 576, "uri": "v0300fg10000cbcl7vjc77uahfnntpkg", "url_key": "v0300fg10000cbcl7vjc77uahfnntpkg_bytevc1_540p_1026722", "url_list": ["https://v5-dy-o-abtest.zjcdn.com/aa7594785f4a468f0b8ac055fadee75b/63b02258/video/tos/cn/tos-cn-ve-15c001-alinc2/2754c8ed70324bae99c5373911a813b4/?a=1128&ch=26&cr=3&dr=0&lr=all&cd=0%7C0%7C0%7C3&cv=1&br=1002&bt=1002&cs=2&ds=6&ft=G__kkZZI0rd12NhGV---VozfuLYkDQIkaYlv&mime_type=video_mp4&qs=11&rc=NDozaDVlZWZnZjU5aWZmOkBpanNxaWQ6ZnlvZTMzNGkzM0AxLzMvXi5iNi8xYDIwYDZjYSNocWtlcjRnNGBgLS1kLTBzcw%3D%3D&l=2022123118471393DDD44DD8533F737F96&btag=b0000&cc=46", "https://v26.douyinvod.com/4e6d634e142c25265fac21b751fa500f/63b02258/video/tos/cn/tos-cn-ve-15c001-alinc2/2754c8ed70324bae99c5373911a813b4/?a=1128&ch=26&cr=3&dr=0&lr=all&cd=0%7C0%7C0%7C3&cv=1&br=1002&bt=1002&cs=2&ds=6&ft=G__kkZZI0rd12NhGV---VozfuLYkDQIkaYlv&mime_type=video_mp4&qs=11&rc=NDozaDVlZWZnZjU5aWZmOkBpanNxaWQ6ZnlvZTMzNGkzM0AxLzMvXi5iNi8xYDIwYDZjYSNocWtlcjRnNGBgLS1kLTBzcw%3D%3D&l=2022123118471393DDD44DD8533F737F96&btag=b0000&cc=2a", "https://api.amemv.com/aweme/v1/play/?video_id=v0300fg10000cbcl7vjc77uahfnntpkg&line=0&file_id=f79ccc3f56c24c2d9ceb1ba22e602741&sign=d6e63b46fb16655c41aa00aa58cadc65&is_play_url=1&source=PackSourceEnum_AWEME_DETAIL", "https://api5-normal-dsa.amemv.com/aweme/v1/play/?video_id=v0300fg10000cbcl7vjc77uahfnntpkg&line=1&file_id=f79ccc3f56c24c2d9ceb1ba22e602741&sign=d6e63b46fb16655c41aa00aa58cadc65&is_play_url=1&source=PackSourceEnum_AWEME_DETAIL"], "width": 1016}, "quality_type": 28}], "cover": {"height": 720, "uri": "tos-cn-p-0015/b87eb83d7d4d40ada8114885ab5ca5b7", "url_list": ["https://p3-sign.douyinpic.com/tos-cn-p-0015/b87eb83d7d4d40ada8114885ab5ca5b7~c5_300x400.webp?x-expires=1673690400&x-signature=IyeR0VP%2FR3mXCswemFla6cmXN3E%3D&from=3213915784_large&s=PackSourceEnum_AWEME_DETAIL&se=false&sc=cover&l=2022123118471393DDD44DD8533F737F96", "https://p26-sign.douyinpic.com/tos-cn-p-0015/b87eb83d7d4d40ada8114885ab5ca5b7~c5_300x400.webp?x-expires=1673690400&x-signature=TVdyy91I9lO9NUxs7aBL5jJvI9A%3D&from=3213915784_large&s=PackSourceEnum_AWEME_DETAIL&se=false&sc=cover&l=2022123118471393DDD44DD8533F737F96", "https://p9-sign.douyinpic.com/tos-cn-p-0015/b87eb83d7d4d40ada8114885ab5ca5b7~c5_300x400.webp?x-expires=1673690400&x-signature=piD%2FZQZT8alnLNaxQLLfO%2FUvaV8%3D&from=3213915784_large&s=PackSourceEnum_AWEME_DETAIL&se=false&sc=cover&l=2022123118471393DDD44DD8533F737F96", "https://p3-sign.douyinpic.com/tos-cn-p-0015/b87eb83d7d4d40ada8114885ab5ca5b7~c5_300x400.jpeg?x-expires=1673690400&x-signature=MOwv7oKPyoKaTW8LxLcjTxdVMLM%3D&from=3213915784_large&s=PackSourceEnum_AWEME_DETAIL&se=false&sc=cover&l=2022123118471393DDD44DD8533F737F96"], "width": 720}, "cover_original_scale": {"height": 720, "uri": "tos-cn-p-0015/b87eb83d7d4d40ada8114885ab5ca5b7", "url_list": ["https://p3-sign.douyinpic.com/tos-cn-p-0015/b87eb83d7d4d40ada8114885ab5ca5b7~tplv-dy-360p.webp?x-expires=1673690400&x-signature=t5bdcYYdiXzd4Yl4vwDsA%2BrjO%2FY%3D&from=3213915784&se=false&biz_tag=feed_cover&l=2022123118471393DDD44DD8533F737F96", "https://p26-sign.douyinpic.com/tos-cn-p-0015/b87eb83d7d4d40ada8114885ab5ca5b7~tplv-dy-360p.webp?x-expires=1673690400&x-signature=iHGA%2BbYyJfvlg2vX79l7jxMns1Q%3D&from=3213915784&se=false&biz_tag=feed_cover&l=2022123118471393DDD44DD8533F737F96", "https://p9-sign.douyinpic.com/tos-cn-p-0015/b87eb83d7d4d40ada8114885ab5ca5b7~tplv-dy-360p.webp?x-expires=1673690400&x-signature=6rz9cx6Shko0jIt2TzMXs0TrrAQ%3D&from=3213915784&se=false&biz_tag=feed_cover&l=2022123118471393DDD44DD8533F737F96", "https://p3-sign.douyinpic.com/tos-cn-p-0015/b87eb83d7d4d40ada8114885ab5ca5b7~tplv-dy-360p.jpeg?x-expires=1673690400&x-signature=4nOf025GMGnsVeQPjFADpWJjHXQ%3D&from=3213915784&se=false&biz_tag=feed_cover&l=2022123118471393DDD44DD8533F737F96"], "width": 720}, "duration": 278315, "dynamic_cover": {"height": 720, "uri": "tos-cn-p-0015/06ff447b3c49405495ffae9e22db8070_1658410078", "url_list": ["https://p9-sign.douyinpic.com/obj/tos-cn-p-0015/06ff447b3c49405495ffae9e22db8070_1658410078?x-expires=1673690400&x-signature=Eiig1XuUwoqCOb46OLBUyemqM%2FU%3D&from=3213915784_large", "https://p3-sign.douyinpic.com/obj/tos-cn-p-0015/06ff447b3c49405495ffae9e22db8070_1658410078?x-expires=1673690400&x-signature=4Frbc5uv%2FS%2BlTeEDyGXItNIiSK8%3D&from=3213915784_large", "https://p6-sign.douyinpic.com/obj/tos-cn-p-0015/06ff447b3c49405495ffae9e22db8070_1658410078?x-expires=1673690400&x-signature=JEx%2B3soxIbl%2FrqVU5IsrvSrCau4%3D&from=3213915784_large"], "width": 720}, "height": 544, "horizontal_type": 1, "is_h265": 0, "is_long_video": 1, "is_source_HDR": 0, "meta": "{\"loudness\":\"-17.4\",\"peak\":\"0.60256\",\"qprf\":\"0.028060629963874817\",\"sr_score\":\"0.000\"}", "origin_cover": {"height": 720, "uri": "tos-cn-p-0015/6a49ea10999445a5a6d9e51614f5a3f4_1658410077", "url_list": ["https://p26-sign.douyinpic.com/tos-cn-p-0015/6a49ea10999445a5a6d9e51614f5a3f4_1658410077~tplv-dy-360p.webp?x-expires=1673690400&x-signature=DhTs67opU9uxHZt88fVJznvkl04%3D&from=3213915784&se=false&biz_tag=feed_cover&l=2022123118471393DDD44DD8533F737F96", "https://p9-sign.douyinpic.com/tos-cn-p-0015/6a49ea10999445a5a6d9e51614f5a3f4_1658410077~tplv-dy-360p.webp?x-expires=1673690400&x-signature=TmH2HZdEm4C9dkgcoSdH56iMSrc%3D&from=3213915784&se=false&biz_tag=feed_cover&l=2022123118471393DDD44DD8533F737F96", "https://p6-sign.douyinpic.com/tos-cn-p-0015/6a49ea10999445a5a6d9e51614f5a3f4_1658410077~tplv-dy-360p.webp?x-expires=1673690400&x-signature=muq4mLMO9rSz3PvRq7178VWCa5Y%3D&from=3213915784&se=false&biz_tag=feed_cover&l=2022123118471393DDD44DD8533F737F96", "https://p26-sign.douyinpic.com/tos-cn-p-0015/6a49ea10999445a5a6d9e51614f5a3f4_1658410077~tplv-dy-360p.jpeg?x-expires=1673690400&x-signature=uoEwGPQhdbSdDoPuBZ6XOprNuJA%3D&from=3213915784&se=false&biz_tag=feed_cover&l=2022123118471393DDD44DD8533F737F96"], "width": 720}, "play_addr": {"data_size": 46865622, "file_cs": "c:0-302823-86e7|a:v0300fg10000cbcl7vjc77uahfnntpkg", "file_hash": "20b830ad7d11864f455118412403867d", "height": 544, "uri": "v0300fg10000cbcl7vjc77uahfnntpkg", "url_key": "v0300fg10000cbcl7vjc77uahfnntpkg_h264_540p_1347124", "url_list": ["https://v5-dy-o-abtest.zjcdn.com/cc6f606dfb1a79da000013afd41734b2/63b02258/video/tos/cn/tos-cn-ve-15c001-alinc2/5d8f123e17544d18a081ebfe7d4be034/?a=1128&ch=26&cr=3&dr=0&lr=all&cd=0%7C0%7C0%7C3&cv=1&br=1315&bt=1315&cs=0&ds=6&ft=G__kkZZI0rd12NhGV---VozfuLYkDQIkaYlv&mime_type=video_mp4&qs=0&rc=Ojk7aDRkOmg3ZzdkNWQ0N0BpanNxaWQ6ZnlvZTMzNGkzM0AzYGItYDI2NWExYS1hXl8uYSNocWtlcjRnNGBgLS1kLTBzcw%3D%3D&l=2022123118471393DDD44DD8533F737F96&btag=b0000&cc=46", "https://v26.douyinvod.com/7a037eecd1b97bdc808cc4d051b4ad3e/63b02258/video/tos/cn/tos-cn-ve-15c001-alinc2/5d8f123e17544d18a081ebfe7d4be034/?a=1128&ch=26&cr=3&dr=0&lr=all&cd=0%7C0%7C0%7C3&cv=1&br=1315&bt=1315&cs=0&ds=6&ft=G__kkZZI0rd12NhGV---VozfuLYkDQIkaYlv&mime_type=video_mp4&qs=0&rc=Ojk7aDRkOmg3ZzdkNWQ0N0BpanNxaWQ6ZnlvZTMzNGkzM0AzYGItYDI2NWExYS1hXl8uYSNocWtlcjRnNGBgLS1kLTBzcw%3D%3D&l=2022123118471393DDD44DD8533F737F96&btag=b0000&cc=2a", "https://api.amemv.com/aweme/v1/play/?video_id=v0300fg10000cbcl7vjc77uahfnntpkg&line=0&file_id=14b1aad20ad44dd48e975ac10ee8c667&sign=20b830ad7d11864f455118412403867d&is_play_url=1&source=PackSourceEnum_AWEME_DETAIL", "https://api5-normal-dsa.amemv.com/aweme/v1/play/?video_id=v0300fg10000cbcl7vjc77uahfnntpkg&line=1&file_id=14b1aad20ad44dd48e975ac10ee8c667&sign=20b830ad7d11864f455118412403867d&is_play_url=1&source=PackSourceEnum_AWEME_DETAIL"], "width": 960}, "play_addr_265": {"data_size": 35719033, "file_cs": "c:0-303761-fd9b|a:v0300fg10000cbcl7vjc77uahfnntpkg", "file_hash": "d6e63b46fb16655c41aa00aa58cadc65", "height": 576, "uri": "v0300fg10000cbcl7vjc77uahfnntpkg", "url_key": "v0300fg10000cbcl7vjc77uahfnntpkg_bytevc1_540p_1026722", "url_list": ["https://v5-dy-o-abtest.zjcdn.com/aa7594785f4a468f0b8ac055fadee75b/63b02258/video/tos/cn/tos-cn-ve-15c001-alinc2/2754c8ed70324bae99c5373911a813b4/?a=1128&ch=26&cr=3&dr=0&lr=all&cd=0%7C0%7C0%7C3&cv=1&br=1002&bt=1002&cs=2&ds=6&ft=G__kkZZI0rd12NhGV---VozfuLYkDQIkaYlv&mime_type=video_mp4&qs=11&rc=NDozaDVlZWZnZjU5aWZmOkBpanNxaWQ6ZnlvZTMzNGkzM0AxLzMvXi5iNi8xYDIwYDZjYSNocWtlcjRnNGBgLS1kLTBzcw%3D%3D&l=2022123118471393DDD44DD8533F737F96&btag=b0000&cc=46", "https://v26.douyinvod.com/4e6d634e142c25265fac21b751fa500f/63b02258/video/tos/cn/tos-cn-ve-15c001-alinc2/2754c8ed70324bae99c5373911a813b4/?a=1128&ch=26&cr=3&dr=0&lr=all&cd=0%7C0%7C0%7C3&cv=1&br=1002&bt=1002&cs=2&ds=6&ft=G__kkZZI0rd12NhGV---VozfuLYkDQIkaYlv&mime_type=video_mp4&qs=11&rc=NDozaDVlZWZnZjU5aWZmOkBpanNxaWQ6ZnlvZTMzNGkzM0AxLzMvXi5iNi8xYDIwYDZjYSNocWtlcjRnNGBgLS1kLTBzcw%3D%3D&l=2022123118471393DDD44DD8533F737F96&btag=b0000&cc=2a", "https://api.amemv.com/aweme/v1/play/?video_id=v0300fg10000cbcl7vjc77uahfnntpkg&line=0&file_id=f79ccc3f56c24c2d9ceb1ba22e602741&sign=d6e63b46fb16655c41aa00aa58cadc65&is_play_url=1&source=PackSourceEnum_AWEME_DETAIL", "https://api5-normal-dsa.amemv.com/aweme/v1/play/?video_id=v0300fg10000cbcl7vjc77uahfnntpkg&line=1&file_id=f79ccc3f56c24c2d9ceb1ba22e602741&sign=d6e63b46fb16655c41aa00aa58cadc65&is_play_url=1&source=PackSourceEnum_AWEME_DETAIL"], "width": 1016}, "play_addr_h264": {"data_size": 46865622, "file_cs": "c:0-302823-86e7|a:v0300fg10000cbcl7vjc77uahfnntpkg", "file_hash": "20b830ad7d11864f455118412403867d", "height": 544, "uri": "v0300fg10000cbcl7vjc77uahfnntpkg", "url_key": "v0300fg10000cbcl7vjc77uahfnntpkg_h264_540p_1347124", "url_list": ["https://v5-dy-o-abtest.zjcdn.com/cc6f606dfb1a79da000013afd41734b2/63b02258/video/tos/cn/tos-cn-ve-15c001-alinc2/5d8f123e17544d18a081ebfe7d4be034/?a=1128&ch=26&cr=3&dr=0&lr=all&cd=0%7C0%7C0%7C3&cv=1&br=1315&bt=1315&cs=0&ds=6&ft=G__kkZZI0rd12NhGV---VozfuLYkDQIkaYlv&mime_type=video_mp4&qs=0&rc=Ojk7aDRkOmg3ZzdkNWQ0N0BpanNxaWQ6ZnlvZTMzNGkzM0AzYGItYDI2NWExYS1hXl8uYSNocWtlcjRnNGBgLS1kLTBzcw%3D%3D&l=2022123118471393DDD44DD8533F737F96&btag=b0000&cc=46", "https://v26.douyinvod.com/7a037eecd1b97bdc808cc4d051b4ad3e/63b02258/video/tos/cn/tos-cn-ve-15c001-alinc2/5d8f123e17544d18a081ebfe7d4be034/?a=1128&ch=26&cr=3&dr=0&lr=all&cd=0%7C0%7C0%7C3&cv=1&br=1315&bt=1315&cs=0&ds=6&ft=G__kkZZI0rd12NhGV---VozfuLYkDQIkaYlv&mime_type=video_mp4&qs=0&rc=Ojk7aDRkOmg3ZzdkNWQ0N0BpanNxaWQ6ZnlvZTMzNGkzM0AzYGItYDI2NWExYS1hXl8uYSNocWtlcjRnNGBgLS1kLTBzcw%3D%3D&l=2022123118471393DDD44DD8533F737F96&btag=b0000&cc=2a", "https://api.amemv.com/aweme/v1/play/?video_id=v0300fg10000cbcl7vjc77uahfnntpkg&line=0&file_id=14b1aad20ad44dd48e975ac10ee8c667&sign=20b830ad7d11864f455118412403867d&is_play_url=1&source=PackSourceEnum_AWEME_DETAIL", "https://api5-normal-dsa.amemv.com/aweme/v1/play/?video_id=v0300fg10000cbcl7vjc77uahfnntpkg&line=1&file_id=14b1aad20ad44dd48e975ac10ee8c667&sign=20b830ad7d11864f455118412403867d&is_play_url=1&source=PackSourceEnum_AWEME_DETAIL"], "width": 960}, "ratio": "540p", "video_model": "", "width": 960}, "video_labels": null, "video_tag": [{"level": 1, "tag_id": 2009, "tag_name": "人文社科"}, {"level": 2, "tag_id": 2009001, "tag_name": "传统文化"}, {"level": 3, "tag_id": 2009001002, "tag_name": "曲艺"}], "video_text": [], "wanna_tag": {}}